matrix_synapse_testutils/__init__.py
matrix_synapse_testutils/server.py
matrix_synapse_testutils/unittest.py
matrix_synapse_testutils/utils.py
matrix_synapse_testutils/config/__init__.py
matrix_synapse_testutils/config/utils.py
matrix_synapse_testutils/rest/__init__.py
matrix_synapse_testutils/rest/client/__init__.py
matrix_synapse_testutils/rest/client/utils.py
matrix_synapse_testutils/test_utils/__init__.py
matrix_synapse_testutils/test_utils/event_injection.py
matrix_synapse_testutils/test_utils/html_parsers.py
matrix_synapse_testutils/test_utils/logging_setup.py
matrix_synapse_testutils/test_utils/oidc.py
matrix_synapse_testutils-1.96.1.0.dist-info/LICENSE
matrix_synapse_testutils-1.96.1.0.dist-info/METADATA
matrix_synapse_testutils-1.96.1.0.dist-info/WHEEL
matrix_synapse_testutils-1.96.1.0.dist-info/top_level.txt
matrix_synapse_testutils-1.96.1.0.dist-info/RECORD
