Metadata-Version: 2.1
Name: matrix-synapse-testutils
Version: 1.96.1.0
Summary: Testing utils extracted from matrix-synapse to be reused in plugins
Author: Julian Hille
Maintainer: Julian Hille
License: Apache License
Project-URL: homepage, https://github.com/julianhille/matrix-synapse-testutils
Project-URL: documentation, https://github.com/julianhille/matrix-synapse-testutils
Project-URL: repository, https://github.com/julianhille/matrix-synapse-testutils
Keywords: matrix,synapse,testutils
Classifier: Topic :: Software Development
Requires-Python: >=3.7
License-File: LICENSE
Requires-Dist: matrix-synapse[test] ==1.96.1
